README.md
setup.py
dynamicgraphviz/__init__.py
dynamicgraphviz.egg-info/PKG-INFO
dynamicgraphviz.egg-info/SOURCES.txt
dynamicgraphviz.egg-info/dependency_links.txt
dynamicgraphviz.egg-info/requires.txt
dynamicgraphviz.egg-info/top_level.txt
dynamicgraphviz/exceptions/__init__.py
dynamicgraphviz/exceptions/graph_errors.py
dynamicgraphviz/graph/__init__.py
dynamicgraphviz/graph/directedgraph.py
dynamicgraphviz/graph/graph.py
dynamicgraphviz/graph/undirectedgraph.py
dynamicgraphviz/gui/__init__.py
dynamicgraphviz/gui/graphDrawer.py
dynamicgraphviz/gui/animations/__init__.py
dynamicgraphviz/gui/animations/easing_animations.py