Metadata-Version: 1.0
Name: dynamicgraphviz
Version: 0.8.0
Summary: A dynamic graph drawer with Gtk and Cairo
Home-page: https://github.com/mouton5000/dynamicgraphviz
Author: Dimitri Watel
Author-email: patatemouton@gmail.com
License: MIT
Platform: UNKNOWN
